falsy/__init__.py
falsy/falsy.py
falsy/jlog/__init__.py
falsy/jlog/filters.py
falsy/jlog/formatters.py
falsy/jlog/jlog.py
falsy/jlog/test.py
falsy/loader/__init__.py
falsy/loader/func.py
falsy/loader/task.py
falsy/loader/yaml.py
falsy/netboy/__init__.py
falsy/netboy/chromeboy.py
falsy/netboy/curl_loop.py
falsy/netboy/curl_result.py
falsy/netboy/fetch.py
falsy/netboy/netboy.py
falsy/netboy/one.py
falsy/netboy/request.py
falsy/netboy/run.py
falsy/netboy/simple.py
falsy/netboy/utils.py
falsy/swagger_proxy/__init__.py
falsy/swagger_proxy/middleware.py
falsy/swagger_proxy/operator_loader.py
falsy/swagger_proxy/spec_loader.py
falsy/swagger_proxy/swagger_server.py
falsy/swagger_proxy/vendors/dist_bootstrap/1.json
falsy/swagger_proxy/vendors/dist_bootstrap/index.html
falsy/swagger_proxy/vendors/dist_bootstrap/menu.json
falsy/swagger_proxy/vendors/dist_bootstrap/webjars/drore-document-ui/ace/ace.min.css
falsy/swagger_proxy/vendors/dist_bootstrap/webjars/drore-document-ui/ace/ace.min.js
falsy/swagger_proxy/vendors/dist_bootstrap/webjars/drore-document-ui/ace/bootstrap.min.js
falsy/swagger_proxy/vendors/dist_bootstrap/webjars/drore-document-ui/bootstrap/css/bootstrap.min.css
falsy/swagger_proxy/vendors/dist_bootstrap/webjars/drore-document-ui/bootstrap/css/bootstrap.min.css.map
falsy/swagger_proxy/vendors/dist_bootstrap/webjars/drore-document-ui/bootstrap/fonts/glyphicons-halflings-regular.eot
falsy/swagger_proxy/vendors/dist_bootstrap/webjars/drore-document-ui/bootstrap/fonts/glyphicons-halflings-regular.svg
falsy/swagger_proxy/vendors/dist_bootstrap/webjars/drore-document-ui/bootstrap/fonts/glyphicons-halflings-regular.ttf
falsy/swagger_proxy/vendors/dist_bootstrap/webjars/drore-document-ui/bootstrap/fonts/glyphicons-halflings-regular.woff
falsy/swagger_proxy/vendors/dist_bootstrap/webjars/drore-document-ui/bootstrap/fonts/glyphicons-halflings-regular.woff2
falsy-2017.8.1.dev123.dist-info/DESCRIPTION.rst
falsy-2017.8.1.dev123.dist-info/METADATA
falsy-2017.8.1.dev123.dist-info/RECORD
falsy-2017.8.1.dev123.dist-info/WHEEL
falsy-2017.8.1.dev123.dist-info/metadata.json
falsy-2017.8.1.dev123.dist-info/top_level.txt
