Metadata-Version: 2.0
Name: falsy
Version: 2017.8.1.dev123
Summary: falcon.swagger.yaml
Home-page: UNKNOWN
Author: Jesse MENG (dameng/pingf)
Author-email: pingf0@gmail.com
License: UNKNOWN
Platform: UNKNOWN
Classifier: License :: OSI Approved :: Apache Software License
Classifier: License :: OSI Approved :: MIT License
Classifier: Operating System :: POSIX :: Linux
Classifier: Programming Language :: Python :: 3
Classifier: Programming Language :: Python :: 3.4
Classifier: Programming Language :: Python :: 3.5
Classifier: Programming Language :: Python :: 3.6
Requires-Dist: falcon
Requires-Dist: PyYAML
Requires-Dist: Jinja2
Requires-Dist: gunicorn
